huza/__init__.py
huza/base/__init__.py
huza/base/action.py
huza/base/dockview.py
huza/base/mainwindow.py
huza/base/mainwindow_run.py
huza/base/widget.py
huza/cli/__init__.py
huza/cli/shell.py
huza/icons/__init__.py
huza/icons/iconbase.py
huza/icons/iconcore.py
huza/icons/img.py
huza/icons/images/__init__.py
huza/icons/images/cae.py
huza/icons/images/freecad.py
huza/icons/images/icon1.py
huza/icons/images/icon10.py
huza/icons/images/icon11.py
huza/icons/images/icon12.py
huza/icons/images/icon13.py
huza/icons/images/icon2.py
huza/icons/images/icon3.py
huza/icons/images/icon4.py
huza/icons/images/icon5.py
huza/icons/images/icon6.py
huza/icons/images/icon7.py
huza/icons/images/icon8.py
huza/icons/images/icon9.py
huza/icons/images/img.py
huza/icons/images/img1.py
huza/icons/images/img3.py
huza/icons/images/matlab.py
huza/icons/images/paraview.py
huza/icons/images/pointwise.py
huza/mainwindow/__init__.py
huza/mainwindow/main.py
huza/mainwindow/main_actions.py
huza/mainwindow/main_docks.py
huza/mainwindow/main_ribbon.py
huza/puis/__init__.py
huza/puis/showicon.py
huza/ribbon/RibbonButton.py
huza/ribbon/RibbonPane.py
huza/ribbon/RibbonTab.py
huza/ribbon/RibbonWidget.py
huza/ribbon/__init__.py
huza/ribbon/scale.py
huza/ribbon/qss/__init__.py
huza/ribbon/qss/default_qss.py
huza/ribbon/qss/mainqss.py
huza/ribbon/qss/ribbonpaneqss.py
huza/ribbon/qss/ribbonqss.py
huza/ribbon/qss/ribbonsmallbuttonqss.py
huza/ribbon/qss/ribbosbutton.py
huza/scripts/__init__.py
huza/scripts/img2base64.py
huza/splash/__init__.py
huza/splash/splash.py
huza/util/__init__.py
huza/util/buildui.py
huza/util/constant.py
huza/util/mainui.py
huza/util/version.py
huza-0.4.18.data/data/nsis/nsis.nsi
huza-0.4.18.dist-info/LICENSE
huza-0.4.18.dist-info/METADATA
huza-0.4.18.dist-info/WHEEL
huza-0.4.18.dist-info/entry_points.txt
huza-0.4.18.dist-info/top_level.txt
huza-0.4.18.dist-info/zip-safe
huza-0.4.18.dist-info/RECORD
