Metadata-Version: 2.1
Name: huza
Version: 0.4.18
Summary: Self-use pyqt framework
Home-page: https://github.com/huyidao625/Huza
Author: hufei
Author-email: hufei625@qq.com
License: MIT License
Project-URL: Wiki, https://www.hudh.cn
Classifier: Development Status :: 4 - Beta
Classifier: Intended Audience :: Developers
Classifier: License :: OSI Approved :: MIT License
Classifier: Environment :: X11 Applications :: Qt
Classifier: Programming Language :: Python
Classifier: Programming Language :: Python :: 3.6
Classifier: Programming Language :: Python :: 3.7
Classifier: Programming Language :: Python :: 3.8
Classifier: Programming Language :: Python :: 3.9
Classifier: Programming Language :: Python :: 3.10
Classifier: Programming Language :: Python :: 3.11
Classifier: Topic :: Software Development :: Libraries
License-File: LICENSE
Requires-Dist: loguru
Requires-Dist: PyQt5
Requires-Dist: pyinstaller
Requires-Dist: toolz
